{"corpusRevision":"20260714.1","groundTruth":{"annotationPolicy":"visible glyph envelope expanded by 10 pixels before geometric transforms","boxes":[[[139.5706787109375,78.96436309814453],[864.274658203125,65.06576538085938],[871.6605224609375,134.46795654296875],[130.11561584472656,148.62979125976562]]],"lines":["LOW CONTRAST 2026"],"source":"project-generated-layout-v1"},"height":220,"id":"generated-low-contrast-perspective","pixelFormat":"bgr8","pixelSha256":"cbc864658ff652114642bbaa4172ea4776d81d1c611d0f6401db27e5536ab9c6","provenance":{"fontRevision":"f8d157532fbfaeda587e826d4cd5b21a49186f7c","generator":"corpus/generate_corpus.py"},"rights":"Generated entirely by project code using Noto Sans CJK under OFL-1.1; the rendered fixture pixels are redistributable with light-ocr.","schemaVersion":"1.0","stride":3000,"tags":["english","digits","low-contrast","uneven-illumination","perspective","single-line"],"width":1000}
